pyabi_filecensus/__init__.py
tests/__init__.py
tests/test_pyabi_filecensus.py
PyABI_FileCensus-5.42.10.dist-info/METADATA
PyABI_FileCensus-5.42.10.dist-info/WHEEL
PyABI_FileCensus-5.42.10.dist-info/top_level.txt
PyABI_FileCensus-5.42.10.dist-info/RECORD
